naludaq_rs-0.2.11.dist-info/METADATA
naludaq_rs-0.2.11.dist-info/WHEEL
naludaq_rs-0.2.11.dist-info/licenses/LICENSE
naludaq_rs/__init__.py
naludaq_rs/__init__.pyi
naludaq_rs/py.typed
naludaq_rs/naludaq_rs.abi3.so
naludaq_rs-0.2.11.dist-info/RECORD
