Metadata-Version: 2.4
Name: naludaq_rs
Version: 0.2.11
License-File: LICENSE
Summary: Rust backend for NaluDAQ
Author: Mitchell Matsumori-Kelly <mitchell@naluscientific.com>, Marcus Luck <marcus@naluscientific.com>
Author-email: Mitchell Matsumori-Kelly <mitchell@naluscientific.com>, Marcus Luck <marcus@naluscientific.com>
